gasp/__init__.py
gasp/boards.py
gasp/cards.py
gasp/color.py
gasp/games.py
gasp/gasp.py
gasp/utils.py
gasp-0.6.2.dist-info/LICENSE.txt
gasp-0.6.2.dist-info/METADATA
gasp-0.6.2.dist-info/WHEEL
gasp-0.6.2.dist-info/top_level.txt
gasp-0.6.2.dist-info/RECORD
