Metadata-Version: 2.1
Name: gasp
Version: 0.6.2
Summary: GASP (Graphics API for Students of Python)
Home-page: https://codeberg.org/GASP/GASP_Code
Author: file: AUTHORS.md
Author-email: jeff.elkner@gmail.com
License: GNU General Public License (GPL)
Project-URL: Bug Tracker, https://codeberg.org/GASP/GASP_Code/issues
Keywords: python,python3,graphics,education,tkinter,pygame
Classifier: Development Status :: 4 - Beta
Classifier: Programming Language :: Python :: 3
Classifier: Intended Audience :: Education
Classifier: License :: OSI Approved :: GNU General Public License (GPL)
Classifier: Operating System :: OS Independent
Classifier: Natural Language :: English
Classifier: Topic :: Education :: Computer Aided Instruction (CAI)
Requires-Python: >=3.6
License-File: LICENSE.txt
Provides-Extra: games
Requires-Dist: pygame (>=2.0.0) ; extra == 'games'
